<?xml version="1.0" encoding="UTF-8"?><directors><director><name>John Krasinski</name><films><film>A Not So Quiet Place</film></films></director><director><name>Ridley Scott</name><films><film>Thelma &amp;amp; Louise</film><film>Blade Runner</film><film>Alien</film></films></director><director><name>Robert Zemeckis</name><films><film>Back to the Future</film><film>Cast Away</film></films></director><director><name>Steven Spielberg</name><films><film>E.T. the Extra-Terrestrial</film><film>The Terminal</film><film>Saving Private Ryan</film></films></director><director><name>Gus Van Sant</name><films><film>Good Will Hunting</film></films></director><director><name>Anthony Minghella</name><films><film>The Talented Mr. Ripley</film></films></director><director><name>Lawrence Kasdan</name><films><film>The Accidental Tourist</film></films></director><director><name>Woody Allen</name><films><film>Match Point</film><film>Vicky Cristina Barcelona</film><film>Annie Hall</film><film>Midnight in Paris</film></films></director><director><name>Anthony Russo</name><films><film>Avengers: Infinity War</film></films></director><director><name>Joe Russo</name><films><film>Avengers: Infinity War</film></films></director><director><name>Tom Hanks</name><films><film>Larry Crowne</film></films></director><director><name>Leopold Lindtberg</name><films><film>The Village</film></films></director><director><name>Mike Nichols</name><films><film>Charlie Wilson's War</film></films></director><director><name>Philip Kaufman</name><films><film>Quills</film></films></director><director><name>James Mangold</name><films><film>Walk the Line</film></films></director><director><name>Garry Marshall</name><films><film>Pretty Woman</film></films></director><director><name>Donald Crisp</name><films><film>The Runaway Bride</film></films></director><director><name>James Anderson</name><films><film>The Runaway Bride</film></films></director><director><name>(uncredited assistant)</name><films><film>The Runaway Bride</film></films></director><director><name>Steven Soderbergh</name><films><film>Ocean's Eleven</film></films></director><director><name>Kelly Asbury</name><films><film>Smurfs: The Lost Village</film></films></director><director><name>John McTiernan</name><films><film>Die Hard with a Vengeance</film></films></director><director><name>Matthew Vaughn</name><films><film>Kick-Ass</film></films></director></directors>